{
  "Main" : {
    "uid" : {
      "type" : "UID",
      "config" : {
        "label" : "Уникальный ID",
        "placeholder" : "uid"
      }
    },
    "subtitle" : {
      "type" : "Text",
      "config" : {
        "label" : "Подзаголовок",
        "placeholder" : "подзаголовок"
      }
    },
    "subtitle_bg" : {
      "type" : "Select",
      "config" : {
        "options" : [ "Синий", "Оранжевый", "Зеленый", "Голубой", "Фиолетовый", "Желтый", "Темно-синий" ],
        "default_value" : "Синий",
        "label" : "Фон подзаголовка"
      }
    },
    "title" : {
      "type" : "Text",
      "config" : {
        "label" : "Заголовок",
        "placeholder" : "название новости"
      }
    },
    "text" : {
      "type" : "Text",
      "config" : {
        "label" : "Текст",
        "placeholder" : "Текст"
      }
    },
    "order" : {
      "type" : "Number",
      "config" : {
        "label" : "Порядок следования",
        "placeholder" : "место в слайдере и в сетке (не обязательно)"
      }
    },
    "main_image" : {
      "type" : "Image",
      "config" : {
        "constraint" : { },
        "thumbnails" : [ ],
        "label" : "Главное изображение"
      }
    }
  }
}